hashable/helpers.py
hashable/equals_builder.py
hashable/__init__.py
hashable/tools.py
hashable/hash_code_builder.py
hashable-0.1.dist-info/top_level.txt
hashable-0.1.dist-info/WHEEL
hashable-0.1.dist-info/DESCRIPTION.rst
hashable-0.1.dist-info/metadata.json
hashable-0.1.dist-info/RECORD
hashable-0.1.dist-info/METADATA
