Metadata-Version: 2.0
Name: hashable
Version: 0.1
Summary: Allow objects to be hashable and comparable by attributes
Home-page: https://github.com/minmax/hashable
Author: Karataev Pavel
Author-email: karataev.pavel@gmail.com
License: MIT
Platform: UNKNOWN
Classifier: Development Status :: 3 - Alpha
Classifier: Intended Audience :: Developers
Classifier: License :: OSI Approved :: MIT License
Classifier: Programming Language :: Python
Classifier: Topic :: Software Development :: Libraries :: Python Modules
